dguard_oss/__init__.py
dguard_oss/cli.py
dguard_oss/config.py
dguard_oss-0.1.2.dist-info/METADATA
dguard_oss-0.1.2.dist-info/WHEEL
dguard_oss-0.1.2.dist-info/entry_points.txt
dguard_oss-0.1.2.dist-info/top_level.txt
dguard_oss-0.1.2.dist-info/RECORD
