Metadata-Version: 2.1
Name: dguard-oss
Version: 0.1.2
Summary: A command-line tool for interacting with MinIO.
Home-page: https://github.com/nuaazs/dguard_oss
Author: Zhao Sheng
Author-email: zhaosheng@lyxxkj.com.cn
License: UNKNOWN
Platform: UNKNOWN
Classifier: Programming Language :: Python :: 3
Classifier: License :: OSI Approved :: MIT License
Classifier: Operating System :: OS Independent
Requires-Python: >=3.6
Requires-Dist: minio (>=7.1.0)
